szio/__init__.py
szio/gta5/Shaders.xml
szio/gta5/ShadersG9ParamsDefaults.json
szio/gta5/ShadersG9TextureNameMapping.json
szio/gta5/__init__.py
szio/gta5/archetypes.py
szio/gta5/assets.py
szio/gta5/bounds.py
szio/gta5/cloths.py
szio/gta5/cwxml/__init__.py
szio/gta5/cwxml/adapters/__init__.py
szio/gta5/cwxml/adapters/_utils.py
szio/gta5/cwxml/adapters/archetype.py
szio/gta5/cwxml/adapters/bound.py
szio/gta5/cwxml/adapters/cloth.py
szio/gta5/cwxml/adapters/drawable.py
szio/gta5/cwxml/adapters/fragment.py
szio/gta5/cwxml/bound.py
szio/gta5/cwxml/clipdictionary.py
szio/gta5/cwxml/cloth.py
szio/gta5/cwxml/drawable.py
szio/gta5/cwxml/fragment.py
szio/gta5/cwxml/navmesh.py
szio/gta5/cwxml/provider.py
szio/gta5/cwxml/ymap.py
szio/gta5/cwxml/ytyp.py
szio/gta5/drawables.py
szio/gta5/fragments.py
szio/gta5/jenkhash.py
szio/gta5/native/__init__.py
szio/gta5/native/adapters/__init__.py
szio/gta5/native/adapters/_utils.py
szio/gta5/native/adapters/archetype.py
szio/gta5/native/adapters/bound.py
szio/gta5/native/adapters/cloth.py
szio/gta5/native/adapters/drawable.py
szio/gta5/native/adapters/drawable_gen9.py
szio/gta5/native/adapters/fragment.py
szio/gta5/native/adapters/fragment_gen9.py
szio/gta5/native/hash_resolver.py
szio/gta5/native/provider.py
szio/gta5/native/provider_gen8.py
szio/gta5/native/provider_gen9.py
szio/gta5/shader.py
szio/gta5/shattermaps.py
szio/types.py
szio/xml/__init__.py
szio/xml/element.py
szio-1.1.0.dev0.dist-info/licenses/LICENSE
szio-1.1.0.dev0.dist-info/WHEEL
szio-1.1.0.dev0.dist-info/METADATA
szio-1.1.0.dev0.dist-info/RECORD
